optquest/OptQuestEngine.dll
optquest/OptQuestLib.dll
optquest/__init__.py
optquest/libOptQuestEngine.so
optquest/libOptQuestLib.so
optquest/optquest.py
optquest-10.0.1.1.dist-info/licenses/LICENSE
optquest-10.0.1.1.dist-info/METADATA
optquest-10.0.1.1.dist-info/WHEEL
optquest-10.0.1.1.dist-info/top_level.txt
optquest-10.0.1.1.dist-info/RECORD
