Metadata-Version: 2.4
Name: optquest
Version: 10.0.1.1
Summary: Python interface to OptQuest optimization engine
Author-email: "OptTek Systems, Inc" <python@opttek.com>
Project-URL: Homepage, https://www.opttek.com/products/optquest/
Keywords: optimization,engine,solver
Classifier: Programming Language :: Python :: 3
Classifier: Operating System :: Microsoft :: Windows
Classifier: Operating System :: POSIX :: Linux
Classifier: Topic :: Scientific/Engineering
Classifier: Topic :: Scientific/Engineering :: Artificial Intelligence
Classifier: Topic :: Scientific/Engineering :: Mathematics
Requires-Python: >=3.8
License-File: LICENSE
Dynamic: license-file
